langs/__init__.py
langs-0.1.1.dist-info/LICENSE
langs-0.1.1.dist-info/METADATA
langs-0.1.1.dist-info/WHEEL
langs-0.1.1.dist-info/top_level.txt
langs-0.1.1.dist-info/RECORD
