Metadata-Version: 2.1
Name: langs
Version: 0.1.1
Summary: tools for managing l10n strings
Home-page: https://github.com/usernein/langs
Author: Cezar H.
License: MIT
Platform: UNKNOWN
Classifier: Development Status :: 4 - Beta
Classifier: License :: OSI Approved :: MIT License
Classifier: Operating System :: Unix
Classifier: Programming Language :: Python :: 3 :: Only
Classifier: Topic :: Software Development :: Localization
Requires-Python: >=3.6
